{
	"info": {
		"_postman_id": "4f3ab60e-32c3-40b3-afeb-2c43080703fc",
		"name": "[API] smartplant-care",
		"schema": "https://schema.getpostman.com/json/collection/v2.1.0/collection.json",
		"_exporter_id": "21400179",
		"_collection_link": "https://warped-space-243623.postman.co/workspace/My-Workspace~62d2858b-7c4e-4c12-8fa9-abec3c43e63e/collection/21400179-4f3ab60e-32c3-40b3-afeb-2c43080703fc?action=share&source=collection_link&creator=21400179"
	},
	"item": [
		{
			"name": "Authentication",
			"item": [
				{
					"name": "Registration",
					"event": [
						{
							"listen": "test",
							"script": {
								"exec": [
									""
								],
								"type": "text/javascript"
							}
						}
					],
					"request": {
						"auth": {
							"type": "noauth"
						},
						"method": "POST",
						"header": [],
						"body": {
							"mode": "raw",
							"raw": "{\n    \"name\": \"Moch Ihsan Saepulloh\",\n    \"email\":\"mihsans972@gmail.com\",\n    \"password\":\"#Pass123\"\n}",
							"options": {
								"raw": {
									"language": "json"
								}
							}
						},
						"url": {
							"raw": "{{url}}/registration",
							"host": [
								"{{url}}"
							],
							"path": [
								"registration"
							]
						}
					},
					"response": []
				},
				{
					"name": "Login",
					"event": [
						{
							"listen": "test",
							"script": {
								"exec": [
									"var jsonData = pm.response.json();\r",
									"pm.globals.set(\"token\", jsonData.data.token);\r",
									""
								],
								"type": "text/javascript"
							}
						}
					],
					"request": {
						"auth": {
							"type": "noauth"
						},
						"method": "POST",
						"header": [],
						"body": {
							"mode": "raw",
							"raw": "{\n    \"email\":\"superadmin@mailinator.com\",\n    \"password\":\"#Pass123\"\n}",
							"options": {
								"raw": {
									"language": "json"
								}
							}
						},
						"url": {
							"raw": "{{url}}/login",
							"host": [
								"{{url}}"
							],
							"path": [
								"login"
							]
						}
					},
					"response": []
				},
				{
					"name": "Logout",
					"event": [
						{
							"listen": "test",
							"script": {
								"exec": [
									""
								],
								"type": "text/javascript"
							}
						}
					],
					"request": {
						"auth": {
							"type": "noauth"
						},
						"method": "POST",
						"header": [],
						"url": {
							"raw": "{{url}}/logout",
							"host": [
								"{{url}}"
							],
							"path": [
								"logout"
							]
						}
					},
					"response": []
				}
			],
			"auth": {
				"type": "noauth"
			},
			"event": [
				{
					"listen": "prerequest",
					"script": {
						"type": "text/javascript",
						"exec": [
							""
						]
					}
				},
				{
					"listen": "test",
					"script": {
						"type": "text/javascript",
						"exec": [
							""
						]
					}
				}
			]
		},
		{
			"name": "Master Data",
			"item": [
				{
					"name": "Plant Category",
					"item": [
						{
							"name": "Index Plant Category Data",
							"event": [
								{
									"listen": "test",
									"script": {
										"exec": [
											""
										],
										"type": "text/javascript"
									}
								}
							],
							"request": {
								"auth": {
									"type": "noauth"
								},
								"method": "GET",
								"header": [],
								"url": {
									"raw": "{{url}}/master-data/plant-category",
									"host": [
										"{{url}}"
									],
									"path": [
										"master-data",
										"plant-category"
									]
								}
							},
							"response": []
						},
						{
							"name": "Store Plant Category",
							"event": [
								{
									"listen": "test",
									"script": {
										"exec": [
											""
										],
										"type": "text/javascript"
									}
								}
							],
							"request": {
								"auth": {
									"type": "bearer",
									"bearer": [
										{
											"key": "token",
											"value": "{{token}}",
											"type": "string"
										}
									]
								},
								"method": "POST",
								"header": [],
								"body": {
									"mode": "raw",
									"raw": "{\r\n    \"name\": \"Sample Plant Category 1\"\r\n}",
									"options": {
										"raw": {
											"language": "json"
										}
									}
								},
								"url": {
									"raw": "{{url}}/master-data/plant-category",
									"host": [
										"{{url}}"
									],
									"path": [
										"master-data",
										"plant-category"
									]
								}
							},
							"response": []
						},
						{
							"name": "Get Specific Plant Category",
							"event": [
								{
									"listen": "test",
									"script": {
										"exec": [
											""
										],
										"type": "text/javascript"
									}
								}
							],
							"request": {
								"auth": {
									"type": "noauth"
								},
								"method": "GET",
								"header": [],
								"url": {
									"raw": "{{url}}/master-data/plant-category/1",
									"host": [
										"{{url}}"
									],
									"path": [
										"master-data",
										"plant-category",
										"1"
									]
								}
							},
							"response": []
						},
						{
							"name": "Update Plant Category",
							"event": [
								{
									"listen": "test",
									"script": {
										"exec": [
											""
										],
										"type": "text/javascript"
									}
								}
							],
							"request": {
								"auth": {
									"type": "bearer",
									"bearer": [
										{
											"key": "token",
											"value": "{{token}}",
											"type": "string"
										}
									]
								},
								"method": "PUT",
								"header": [],
								"body": {
									"mode": "raw",
									"raw": "{\r\n    \"name\": \"Sample Plant Category 1 Updated\"\r\n}",
									"options": {
										"raw": {
											"language": "json"
										}
									}
								},
								"url": {
									"raw": "{{url}}/master-data/plant-category/1",
									"host": [
										"{{url}}"
									],
									"path": [
										"master-data",
										"plant-category",
										"1"
									]
								}
							},
							"response": []
						},
						{
							"name": "Delete Plant Category",
							"event": [
								{
									"listen": "test",
									"script": {
										"exec": [
											""
										],
										"type": "text/javascript"
									}
								}
							],
							"request": {
								"auth": {
									"type": "bearer",
									"bearer": [
										{
											"key": "token",
											"value": "{{token}}",
											"type": "string"
										}
									]
								},
								"method": "DELETE",
								"header": [],
								"url": {
									"raw": "{{url}}/master-data/plant-category/1",
									"host": [
										"{{url}}"
									],
									"path": [
										"master-data",
										"plant-category",
										"1"
									]
								}
							},
							"response": []
						}
					],
					"auth": {
						"type": "noauth"
					},
					"event": [
						{
							"listen": "prerequest",
							"script": {
								"type": "text/javascript",
								"exec": [
									""
								]
							}
						},
						{
							"listen": "test",
							"script": {
								"type": "text/javascript",
								"exec": [
									""
								]
							}
						}
					]
				},
				{
					"name": "Plant",
					"item": [
						{
							"name": "Index Plant Data",
							"event": [
								{
									"listen": "test",
									"script": {
										"exec": [
											""
										],
										"type": "text/javascript"
									}
								}
							],
							"request": {
								"auth": {
									"type": "noauth"
								},
								"method": "GET",
								"header": [],
								"url": {
									"raw": "{{url}}/master-data/plant",
									"host": [
										"{{url}}"
									],
									"path": [
										"master-data",
										"plant"
									]
								}
							},
							"response": []
						},
						{
							"name": "Store Plant",
							"event": [
								{
									"listen": "test",
									"script": {
										"exec": [
											""
										],
										"type": "text/javascript"
									}
								}
							],
							"request": {
								"auth": {
									"type": "bearer",
									"bearer": [
										{
											"key": "token",
											"value": "{{token}}",
											"type": "string"
										}
									]
								},
								"method": "POST",
								"header": [],
								"body": {
									"mode": "raw",
									"raw": "{\r\n    \"plant_category_id\": 1,\r\n    \"name\": \"sample name\",\r\n    \"scientific_name\": \"sample scientific name\",\r\n    \"habitat\": \"sample habitat\",\r\n    \"benefits\": \"sample benefits\",\r\n    \"nutritional_value\": \"sample nutritional value\",\r\n    \"pests_and_diseases\": \"sampe pests and diseases\",\r\n    \"cultivation_techniques\": \"sample cultivation techniques\"\r\n}",
									"options": {
										"raw": {
											"language": "json"
										}
									}
								},
								"url": {
									"raw": "{{url}}/master-data/plant",
									"host": [
										"{{url}}"
									],
									"path": [
										"master-data",
										"plant"
									]
								}
							},
							"response": []
						},
						{
							"name": "Get Specific Plant",
							"event": [
								{
									"listen": "test",
									"script": {
										"exec": [
											""
										],
										"type": "text/javascript"
									}
								}
							],
							"request": {
								"auth": {
									"type": "noauth"
								},
								"method": "GET",
								"header": [],
								"url": {
									"raw": "{{url}}/master-data/plant/1",
									"host": [
										"{{url}}"
									],
									"path": [
										"master-data",
										"plant",
										"1"
									]
								}
							},
							"response": []
						},
						{
							"name": "Update Plant",
							"event": [
								{
									"listen": "test",
									"script": {
										"exec": [
											""
										],
										"type": "text/javascript"
									}
								}
							],
							"request": {
								"auth": {
									"type": "bearer",
									"bearer": [
										{
											"key": "token",
											"value": "{{token}}",
											"type": "string"
										}
									]
								},
								"method": "PUT",
								"header": [],
								"body": {
									"mode": "raw",
									"raw": "{\r\n    \"plant_category_id\": 1,\r\n    \"name\": \"sample name updated\",\r\n    \"scientific_name\": \"sample scientific name updated\",\r\n    \"habitat\": \"sample habitat updated\",\r\n    \"benefits\": \"sample benefits updated\",\r\n    \"nutritional_value\": \"sample nutritional value updated\",\r\n    \"pests_and_diseases\": \"sampe pests and diseases updated\",\r\n    \"cultivation_techniques\": \"sample cultivation techniques updated\"\r\n}",
									"options": {
										"raw": {
											"language": "json"
										}
									}
								},
								"url": {
									"raw": "{{url}}/master-data/plant/1",
									"host": [
										"{{url}}"
									],
									"path": [
										"master-data",
										"plant",
										"1"
									]
								}
							},
							"response": []
						},
						{
							"name": "Delete Plant",
							"event": [
								{
									"listen": "test",
									"script": {
										"exec": [
											""
										],
										"type": "text/javascript"
									}
								}
							],
							"request": {
								"auth": {
									"type": "bearer",
									"bearer": [
										{
											"key": "token",
											"value": "{{token}}",
											"type": "string"
										}
									]
								},
								"method": "DELETE",
								"header": [],
								"url": {
									"raw": "{{url}}/master-data/plant/1",
									"host": [
										"{{url}}"
									],
									"path": [
										"master-data",
										"plant",
										"1"
									]
								}
							},
							"response": []
						}
					],
					"auth": {
						"type": "noauth"
					},
					"event": [
						{
							"listen": "prerequest",
							"script": {
								"type": "text/javascript",
								"exec": [
									""
								]
							}
						},
						{
							"listen": "test",
							"script": {
								"type": "text/javascript",
								"exec": [
									""
								]
							}
						}
					]
				}
			]
		},
		{
			"name": "Sensor",
			"item": [
				{
					"name": "Index Sensor Data",
					"event": [
						{
							"listen": "test",
							"script": {
								"exec": [
									""
								],
								"type": "text/javascript"
							}
						}
					],
					"request": {
						"auth": {
							"type": "noauth"
						},
						"method": "GET",
						"header": [],
						"url": {
							"raw": "{{url}}/sensor",
							"host": [
								"{{url}}"
							],
							"path": [
								"sensor"
							]
						}
					},
					"response": []
				},
				{
					"name": "Store Plant",
					"event": [
						{
							"listen": "test",
							"script": {
								"exec": [
									""
								],
								"type": "text/javascript"
							}
						}
					],
					"request": {
						"auth": {
							"type": "bearer",
							"bearer": [
								{
									"key": "token",
									"value": "{{token}}",
									"type": "string"
								}
							]
						},
						"method": "POST",
						"header": [],
						"body": {
							"mode": "raw",
							"raw": "{\r\n    \"name\": \"Sample sensor\",\r\n    \"value\": 100,\r\n    \"description\": \"-\"\r\n}",
							"options": {
								"raw": {
									"language": "json"
								}
							}
						},
						"url": {
							"raw": "{{url}}/sensor",
							"host": [
								"{{url}}"
							],
							"path": [
								"sensor"
							]
						}
					},
					"response": []
				},
				{
					"name": "Get Specific Sensor",
					"event": [
						{
							"listen": "test",
							"script": {
								"exec": [
									""
								],
								"type": "text/javascript"
							}
						}
					],
					"request": {
						"auth": {
							"type": "noauth"
						},
						"method": "GET",
						"header": [],
						"url": {
							"raw": "{{url}}/sensor/1",
							"host": [
								"{{url}}"
							],
							"path": [
								"sensor",
								"1"
							]
						}
					},
					"response": []
				},
				{
					"name": "Update Sensor",
					"event": [
						{
							"listen": "test",
							"script": {
								"exec": [
									""
								],
								"type": "text/javascript"
							}
						}
					],
					"request": {
						"auth": {
							"type": "bearer",
							"bearer": [
								{
									"key": "token",
									"value": "{{token}}",
									"type": "string"
								}
							]
						},
						"method": "PUT",
						"header": [],
						"body": {
							"mode": "raw",
							"raw": "{\r\n    \"name\": \"Sample sensor updated\",\r\n    \"value\": 100,\r\n    \"description\": \"-\"\r\n}",
							"options": {
								"raw": {
									"language": "json"
								}
							}
						},
						"url": {
							"raw": "{{url}}/sensor/1",
							"host": [
								"{{url}}"
							],
							"path": [
								"sensor",
								"1"
							]
						}
					},
					"response": []
				},
				{
					"name": "Update Batch Sensor",
					"event": [
						{
							"listen": "test",
							"script": {
								"exec": [
									""
								],
								"type": "text/javascript"
							}
						}
					],
					"request": {
						"auth": {
							"type": "bearer",
							"bearer": [
								{
									"key": "token",
									"value": "{{token}}",
									"type": "string"
								}
							]
						},
						"method": "PUT",
						"header": [],
						"body": {
							"mode": "raw",
							"raw": "{\r\n    \"sensor1\": 100,\r\n    \"sensor2\": 100,\r\n    \"sensor3\": 100,\r\n    \"sensor4\": 100\r\n}",
							"options": {
								"raw": {
									"language": "json"
								}
							}
						},
						"url": {
							"raw": "{{url}}/sensor/update-batch",
							"host": [
								"{{url}}"
							],
							"path": [
								"sensor",
								"update-batch"
							]
						}
					},
					"response": []
				},
				{
					"name": "Delete Sensor",
					"event": [
						{
							"listen": "test",
							"script": {
								"exec": [
									""
								],
								"type": "text/javascript"
							}
						}
					],
					"request": {
						"auth": {
							"type": "bearer",
							"bearer": [
								{
									"key": "token",
									"value": "{{token}}",
									"type": "string"
								}
							]
						},
						"method": "DELETE",
						"header": [],
						"url": {
							"raw": "{{url}}/sensor/1",
							"host": [
								"{{url}}"
							],
							"path": [
								"sensor",
								"1"
							]
						}
					},
					"response": []
				}
			],
			"auth": {
				"type": "noauth"
			},
			"event": [
				{
					"listen": "prerequest",
					"script": {
						"type": "text/javascript",
						"exec": [
							""
						]
					}
				},
				{
					"listen": "test",
					"script": {
						"type": "text/javascript",
						"exec": [
							""
						]
					}
				}
			]
		}
	]
}